MANIFEST.in
setup.cfg
setup.py
deltasigma/_DocumentNTF.py
deltasigma/_LCoptparam2tf.py
deltasigma/_PlotExampleSpectrum.py
deltasigma/_SIunits.py
deltasigma/__init__.py
deltasigma/_axisLabels.py
deltasigma/_bilogplot.py
deltasigma/_bplogsmooth.py
deltasigma/_bquantize.py
deltasigma/_bunquantize.py
deltasigma/_calculateQTF.py
deltasigma/_calculateSNR.py
deltasigma/_calculateTF.py
deltasigma/_cancelPZ.py
deltasigma/_changeFig.py
deltasigma/_circ_smooth.py
deltasigma/_clans.py
deltasigma/_config.py
deltasigma/_constants.py
deltasigma/_db.py
deltasigma/_dbm.py
deltasigma/_dbp.py
deltasigma/_dbv.py
deltasigma/_delay.py
deltasigma/_designLCBP.py
deltasigma/_ds_f1f2.py
deltasigma/_ds_freq.py
deltasigma/_ds_hann.py
deltasigma/_ds_optzeros.py
deltasigma/_ds_quantize.py
deltasigma/_ds_synNTFobj1.py
deltasigma/_dsclansNTF.py
deltasigma/_evalF0.py
deltasigma/_evalF1.py
deltasigma/_evalMixedTF.py
deltasigma/_evalRPoly.py
deltasigma/_evalTF.py
deltasigma/_evalTFP.py
deltasigma/_figureMagic.py
deltasigma/_frespF1.py
deltasigma/_impL1.py
deltasigma/_infnorm.py
deltasigma/_l1norm.py
deltasigma/_logsmooth.py
deltasigma/_lollipop.py
deltasigma/_mapABCD.py
deltasigma/_mapCtoD.py
deltasigma/_mapQtoR.py
deltasigma/_mapRtoQ.py
deltasigma/_mod1.py
deltasigma/_mod2.py
deltasigma/_nabsH.py
deltasigma/_padb.py
deltasigma/_padl.py
deltasigma/_padr.py
deltasigma/_padt.py
deltasigma/_partitionABCD.py
deltasigma/_peakSNR.py
deltasigma/_plotPZ.py
deltasigma/_plotSpectrum.py
deltasigma/_predictSNR.py
deltasigma/_pulse.py
deltasigma/_realizeNTF.py
deltasigma/_realizeNTF_ct.py
deltasigma/_realizeQNTF.py
deltasigma/_rms.py
deltasigma/_rmsGain.py
deltasigma/_scaleABCD.py
deltasigma/_simulateDSM.py
deltasigma/_simulateDSM_cblas.pyx
deltasigma/_simulateDSM_helper.pxi
deltasigma/_simulateDSM_python.py
deltasigma/_simulateDSM_scipy_blas.pyx
deltasigma/_simulateQDSM.py
deltasigma/_simulateQDSM_core.pxd
deltasigma/_simulateQDSM_core.py
deltasigma/_simulateQSNR.py
deltasigma/_simulateSNR.py
deltasigma.egg-info/PKG-INFO
deltasigma.egg-info/SOURCES.txt
deltasigma.egg-info/dependency_links.txt
deltasigma.egg-info/not-zip-safe
deltasigma.egg-info/requires.txt
deltasigma.egg-info/top_level.txt
