Metadata-Version: 1.1
Name: deltasigma
Version: 0.2.2
Summary: a Python package to synthesize, simulate, scale and map to implementable topologies delta sigma modulators.
Home-page: http://github.com/ggventurini/python-deltasigma
Author: Giuseppe Venturini and others
Author-email: giuseppe.g.venturini@ieee.org
License: BSD
Keywords: delta sigma modulator simulator
Platform: UNKNOWN
Classifier: Development Status :: 5 - Production/Stable
Classifier: Intended Audience :: Education
Classifier: Intended Audience :: Science/Research
Classifier: License :: OSI Approved :: BSD License
Classifier: Operating System :: POSIX
Classifier: Operating System :: POSIX :: Linux
Classifier: Operating System :: Microsoft :: Windows
Classifier: Operating System :: MacOS
Classifier: Natural Language :: English
Classifier: Programming Language :: Python :: 2
Classifier: Programming Language :: Python :: 2.7
Classifier: Programming Language :: Python :: 3
Classifier: Programming Language :: Python :: 3.4
